README.txt
setup.py
gbpfunctests/__init__.py
gbpfunctests.egg-info/PKG-INFO
gbpfunctests.egg-info/SOURCES.txt
gbpfunctests.egg-info/dependency_links.txt
gbpfunctests.egg-info/top_level.txt