Metadata-Version: 1.0
Name: gbpfunctests
Version: 1.0.6
Summary: Created subdirectories testcases & libs, removed the option from suite_run
Home-page: https://github.com/puppet-py/gbpfunctests
Author: jishnu
Author-email: jbanerje@noironetworks.com
License: UNKNOWN
Platform: UNKNOWN
